fastDamerauLevenshtein.cp38-win_amd64.pyd
fastDamerauLevenshtein-1.0.7.dist-info/LICENSE
fastDamerauLevenshtein-1.0.7.dist-info/METADATA
fastDamerauLevenshtein-1.0.7.dist-info/WHEEL
fastDamerauLevenshtein-1.0.7.dist-info/top_level.txt
fastDamerauLevenshtein-1.0.7.dist-info/RECORD
